adminboundarymanager/__init__.py
adminboundarymanager/admin.py
adminboundarymanager/apps.py
adminboundarymanager/errors.py
adminboundarymanager/forms.py
adminboundarymanager/models.py
adminboundarymanager/serializers.py
adminboundarymanager/tests.py
adminboundarymanager/urls.py
adminboundarymanager/utils.py
adminboundarymanager/views.py
adminboundarymanager/wagtail_hooks.py
adminboundarymanager/loaders/__init__.py
adminboundarymanager/loaders/cod_abs_loader.py
adminboundarymanager/loaders/gadm_loader.py
adminboundarymanager/loaders/generic_loader.py
adminboundarymanager/migrations/0001_initial.py
adminboundarymanager/migrations/0002_adminboundarysettings_data_source.py
adminboundarymanager/migrations/0003_alter_adminboundarysettings_data_source.py
adminboundarymanager/migrations/0004_rename_countries_country_and_more.py
adminboundarymanager/migrations/0005_alter_country_country.py
adminboundarymanager/migrations/0006_remove_adminboundary_size_and_more.py
adminboundarymanager/migrations/0007_boundarymenupermission.py
adminboundarymanager/migrations/__init__.py
adminboundarymanager/static/adminboundarymanager/css/maplibre-gl.css
adminboundarymanager/static/adminboundarymanager/js/maplibre-gl.js
adminboundarymanager/templates/adminboundarymanager/boundary_loader.html
adminboundarymanager/templates/adminboundarymanager/boundary_preview.html
adm_boundary_manager-0.3.0.dist-info/METADATA
adm_boundary_manager-0.3.0.dist-info/WHEEL
adm_boundary_manager-0.3.0.dist-info/top_level.txt
adm_boundary_manager-0.3.0.dist-info/RECORD
